examples/api_example.py
examples/demo_key_exchange.py
examples/demo_signing.py
rights_to_secure_hybrid_crypto-1.0.1.dist-info/licenses/LICENSE
src/__init__.py
src/hybrid_kem.py
src/hybrid_signature.py
src/mock_oqs.py
src/utils.py
tests/test_hybrid_kem.py
tests/test_hybrid_signature.py
rights_to_secure_hybrid_crypto-1.0.1.dist-info/METADATA
rights_to_secure_hybrid_crypto-1.0.1.dist-info/WHEEL
rights_to_secure_hybrid_crypto-1.0.1.dist-info/entry_points.txt
rights_to_secure_hybrid_crypto-1.0.1.dist-info/top_level.txt
rights_to_secure_hybrid_crypto-1.0.1.dist-info/RECORD
