Metadata-Version: 2.4
Name: rights-to-secure-hybrid-crypto
Version: 1.0.1
Summary: Production-ready hybrid cryptography combining classical (RSA/ECDSA) with post-quantum (Kyber/Dilithium) algorithms for quantum resistance and backward compatibility
Home-page: https://rightstosecure.com
Author: Praveen Naidu
Author-email: Praveen Naidu <contact@arkaenterprises.com>
Maintainer-email: Praveen Naidu <contact@arkaenterprises.com>
License: MIT
Project-URL: Homepage, https://rightstosecure.com
Project-URL: Documentation, https://academy.rightstosecure.com
Project-URL: Repository, https://github.com/rightstosecure/hybrid-crypto
Project-URL: Bug Tracker, https://github.com/rightstosecure/hybrid-crypto/issues
Keywords: cryptography,post-quantum,quantum-resistant,hybrid,rsa,ecc,ecdsa,kyber,dilithium,security,encryption,signature,key-exchange,kem,rights-to-secure,quantum-safe,quantum-proof
Platform: any
Classifier: Development Status :: 5 - Production/Stable
Classifier: Intended Audience :: Developers
Classifier: Intended Audience :: Information Technology
Classifier: Intended Audience :: System Administrators
Classifier: License :: OSI Approved :: MIT License
Classifier: Operating System :: OS Independent
Classifier: Programming Language :: Python :: 3
Classifier: Programming Language :: Python :: 3.8
Classifier: Programming Language :: Python :: 3.9
Classifier: Programming Language :: Python :: 3.10
Classifier: Programming Language :: Python :: 3.11
Classifier: Programming Language :: Python :: 3.12
Classifier: Topic :: Security :: Cryptography
Classifier: Topic :: Software Development :: Libraries :: Python Modules
Classifier: Topic :: Communications :: Email
Classifier: Topic :: Internet :: WWW/HTTP :: HTTP Servers
Classifier: Topic :: Internet :: WWW/HTTP :: WSGI :: Application
Requires-Python: >=3.8
License-File: LICENSE
Requires-Dist: cryptography>=41.0.0
Requires-Dist: liboqs-python>=0.7.2
Requires-Dist: pytest>=7.0.0
Provides-Extra: dev
Requires-Dist: pytest>=7.0.0; extra == "dev"
Requires-Dist: pytest-cov>=4.0.0; extra == "dev"
Requires-Dist: black>=22.0.0; extra == "dev"
Requires-Dist: flake8>=5.0.0; extra == "dev"
Requires-Dist: mypy>=1.0.0; extra == "dev"
Requires-Dist: sphinx>=5.0.0; extra == "dev"
Requires-Dist: sphinx-rtd-theme>=1.0.0; extra == "dev"
Provides-Extra: api
Requires-Dist: fastapi>=0.100.0; extra == "api"
Requires-Dist: uvicorn>=0.20.0; extra == "api"
Requires-Dist: pydantic>=2.0.0; extra == "api"
Provides-Extra: web
Requires-Dist: flask>=2.3.0; extra == "web"
Requires-Dist: flask-cors>=4.0.0; extra == "web"
Dynamic: author
Dynamic: home-page
Dynamic: license-file
Dynamic: platform
Dynamic: requires-python
